README
setup.py
spcControl/__init__.py
spcControl/__main__.py
spcControl/chamber.py
spcControl/heliospectra.py
spcControl.egg-info/PKG-INFO
spcControl.egg-info/SOURCES.txt
spcControl.egg-info/dependency_links.txt
spcControl.egg-info/requires.txt
spcControl.egg-info/top_level.txt
spcControl/monitor/__init__.py
spcControl/monitor/__main__.py