Metadata-Version: 1.1
Name: spcControl
Version: 0.1rc5
Summary: 
